certbot_dns_plesk/__init__.py
certbot_dns_plesk/dns_plesk.py
certbot_dns_plesk-0.3.0.dist-info/LICENSE
certbot_dns_plesk-0.3.0.dist-info/METADATA
certbot_dns_plesk-0.3.0.dist-info/WHEEL
certbot_dns_plesk-0.3.0.dist-info/entry_points.txt
certbot_dns_plesk-0.3.0.dist-info/top_level.txt
certbot_dns_plesk-0.3.0.dist-info/RECORD
