Metadata-Version: 2.1
Name: certbot-dns-plesk
Version: 0.3.0
Summary: plesk DNS Authenticator plugin for Certbot
Home-page: https://gitlab.com/spike77453/certbot-dns-plesk
Author: Christian Schürmann
Author-email: spike@fedoraproject.org
License: UNKNOWN
Platform: UNKNOWN
Classifier: Development Status :: 4 - Beta
Classifier: Environment :: Plugins
Classifier: Intended Audience :: System Administrators
Classifier: License :: OSI Approved :: GNU General Public License v3 or later (GPLv3+)
Classifier: Operating System :: POSIX :: Linux
Classifier: Programming Language :: Python
Classifier: Programming Language :: Python :: 3
Classifier: Programming Language :: Python :: 3.6
Classifier: Programming Language :: Python :: 3.7
Classifier: Programming Language :: Python :: 3.8
Classifier: Programming Language :: Python :: 3.9
Classifier: Topic :: Internet :: WWW/HTTP
Classifier: Topic :: Security
Classifier: Topic :: System :: Installation/Setup
Classifier: Topic :: System :: Networking
Classifier: Topic :: System :: Systems Administration
Classifier: Topic :: Utilities
Requires-Python: >=3.6
License-File: LICENSE
Requires-Dist: acme (>=0.31.0)
Requires-Dist: certbot (>=1.18.0)
Requires-Dist: dns-lexicon (>=3.2.4)
Requires-Dist: setuptools
Requires-Dist: requests
